[
    {"type":"header","version":"4.9.2","comment":"Export to JSON plugin for PHPMyAdmin"},
    {"type":"database","name":"visin_survey"},
    {"type":"table","name":"jenis","database":"visin_survey","data":
    [
    {"Region":"Pekanbaru","Jenis":"Rumah sakit umum","Tahun":"2018","Jumlah":"19"},
    {"Region":"Pekanbaru","Jenis":"Rumah sakit umum","Tahun":"2019","Jumlah":"23"},
    {"Region":"Pekanbaru","Jenis":"Rumah sakit khusus","Tahun":"2018","Jumlah":"10"},
    {"Region":"Pekanbaru","Jenis":"Rumah sakit khusus","Tahun":"2019","Jumlah":"8"},
    {"Region":"Pekanbaru","Jenis":"Pukesmas rawat inap","Tahun":"2018","Jumlah":"6"},
    {"Region":"Pekanbaru","Jenis":"Pukesmas rawat inap","Tahun":"2019","Jumlah":"6"},
    {"Region":"Pekanbaru","Jenis":"Pukesmas rawat jalan","Tahun":"2018","Jumlah":"15"},
    {"Region":"Pekanbaru","Jenis":"Pukesmas rawat jalan","Tahun":"2019","Jumlah":"15"},
    {"Region":"Pekanbaru","Jenis":"Klinik pratama","Tahun":"2018","Jumlah":"185"},
    {"Region":"Pekanbaru","Jenis":"Klinik pratama","Tahun":"2019","Jumlah":"185"},
    {"Region":"Bengkalis","Jenis":"Rumah sakit umum","Tahun":"2018","Jumlah":"6"},
    {"Region":"Bengkalis","Jenis":"Rumah sakit umum","Tahun":"2019","Jumlah":"7"},
    {"Region":"Bengkalis","Jenis":"Rumah sakit khusus","Tahun":"2018","Jumlah":"1"},
    {"Region":"Bengkalis","Jenis":"Rumah sakit khusus","Tahun":"2019","Jumlah":"0"},
    {"Region":"Bengkalis","Jenis":"Pukesmas rawat inap","Tahun":"2018","Jumlah":"4"},
    {"Region":"Bengkalis","Jenis":"Pukesmas rawat inap","Tahun":"2019","Jumlah":"6"},
    {"Region":"Bengkalis","Jenis":"Pukesmas rawat jalan","Tahun":"2018","Jumlah":"7"},
    {"Region":"Bengkalis","Jenis":"Pukesmas rawat jalan","Tahun":"2019","Jumlah":"12"},
    {"Region":"Bengkalis","Jenis":"Klinik pratama","Tahun":"2018","Jumlah":"23"},
    {"Region":"Bengkalis","Jenis":"Klinik pratama","Tahun":"2019","Jumlah":"23"},
    {"Region":"Rokan Hilir","Jenis":"Rumah sakit umum","Tahun":"2018","Jumlah":"5"},
    {"Region":"Rokan Hilir","Jenis":"Rumah sakit umum","Tahun":"2019","Jumlah":"6"},
    {"Region":"Rokan Hilirs","Jenis":"Rumah sakit khusus","Tahun":"2018","Jumlah":"0"},
    {"Region":"Rokan Hilirs","Jenis":"Rumah sakit khusus","Tahun":"2019","Jumlah":"0"},
    {"Region":"Rokan Hilir","Jenis":"Pukesmas rawat inap","Tahun":"2018","Jumlah":"6"},
    {"Region":"Rokan Hilir","Jenis":"Pukesmas rawat inap","Tahun":"2019","Jumlah":"6"},
    {"Region":"Rokan Hilir","Jenis":"Pukesmas rawat jalan","Tahun":"2018","Jumlah":"11"},
    {"Region":"Rokan Hilir","Jenis":"Pukesmas rawat jalan","Tahun":"2019","Jumlah":"13"},
    {"Region":"Rokan Hilir","Jenis":"Klinik pratama","Tahun":"2018","Jumlah":"22"},
    {"Region":"Rokan Hilir","Jenis":"Klinik pratama","Tahun":"2019","Jumlah":"22"}
    ]
    }
]
    